modaat_console/__init__.py
modaat_console/__main__.py
modaat_console/function.py
modaat_console/modaat.py
modaat_console-0.2.dist-info/LICENSE
modaat_console-0.2.dist-info/METADATA
modaat_console-0.2.dist-info/WHEEL
modaat_console-0.2.dist-info/entry_points.txt
modaat_console-0.2.dist-info/top_level.txt
modaat_console-0.2.dist-info/RECORD
