Metadata-Version: 2.1
Name: modaat-console
Version: 0.2
Summary: Connect to an OPeNDAP service (ERDDAP) and query data and metadata through a simple console menu.
Home-page: https://github.com/CEN-ULaval/modaat
Author: Etienne Godin
Author-email: etienne.godin@cen.ulaval.ca
License: MIT
Keywords: erddap MODAAT OPeNDAP DAP CCADI CEN
Platform: UNKNOWN
Classifier: Development Status :: 3 - Alpha
Classifier: Intended Audience :: Science/Research
Classifier: Intended Audience :: Developers
Classifier: Topic :: Internet
Classifier: License :: OSI Approved :: MIT License
Classifier: Programming Language :: Python
Classifier: Programming Language :: Python :: 3
Classifier: Programming Language :: Python :: 3.10
Classifier: Environment :: Console
Classifier: Natural Language :: English
Classifier: Operating System :: OS Independent
Classifier: Topic :: Scientific/Engineering :: Information Analysis
Classifier: Topic :: Scientific/Engineering :: Atmospheric Science
Requires-Python: >=3.10
License-File: LICENSE
Requires-Dist: requests (>=2.27.1)
Requires-Dist: erddapy
Requires-Dist: pandas (>=1.4)
